MANIFEST.in
README.txt
setup.py
collective/__init__.py
collective.edm.listing.egg-info/PKG-INFO
collective.edm.listing.egg-info/SOURCES.txt
collective.edm.listing.egg-info/dependency_links.txt
collective.edm.listing.egg-info/entry_points.txt
collective.edm.listing.egg-info/namespace_packages.txt
collective.edm.listing.egg-info/not-zip-safe
collective.edm.listing.egg-info/requires.txt
collective.edm.listing.egg-info/top_level.txt
collective/edm/__init__.py
collective/edm/listing/__init__.py
collective/edm/listing/configure.zcml
collective/edm/listing/editpopup.py
collective/edm/listing/interfaces.py
collective/edm/listing/listing.py
collective/edm/listing/listingoptions.py
collective/edm/listing/listingrights.py
collective/edm/listing/quickupload.py
collective/edm/listing/subscribers.py
collective/edm/listing/tests.py
collective/edm/listing/upgrades.py
collective/edm/listing/utils.py
collective/edm/listing/version.txt
collective/edm/listing/locales/collective.edm.listing-manual.pot
collective/edm/listing/locales/collective.edm.listing.pot
collective/edm/listing/locales/update.sh
collective/edm/listing/locales/de/LC_MESSAGES/collective.edm.listing.po
collective/edm/listing/locales/fr/LC_MESSAGES/collective.edm.listing.po
collective/edm/listing/profiles/default/browserlayer.xml
collective/edm/listing/profiles/default/cssregistry.xml
collective/edm/listing/profiles/default/jsregistry.xml
collective/edm/listing/profiles/default/metadata.xml
collective/edm/listing/profiles/default/registry.xml
collective/edm/listing/profiles/default/skins.xml
collective/edm/listing/profiles/default/types/Folder.xml
collective/edm/listing/resources/listing.js
collective/edm/listing/skins/edm_listing_images/history.png
collective/edm/listing/skins/edm_listing_images/history.png.metadata
collective/edm/listing/skins/edm_listing_images/listing-arrowdown.gif
collective/edm/listing/skins/edm_listing_images/listing-arrowdown.gif.metadata
collective/edm/listing/skins/edm_listing_images/listing-arrowup.gif
collective/edm/listing/skins/edm_listing_images/listing-arrowup.gif.metadata
collective/edm/listing/skins/edm_listing_styles/edmlisting.css
collective/edm/listing/templates/batching.pt
collective/edm/listing/templates/editpopup.pt
collective/edm/listing/templates/foldercontents.pt
collective/edm/listing/templates/quickupload.pt
