Metadata-Version: 1.1
Name: collective.edm.listing
Version: 0.10
Summary: A view for folders that provides file-explorer like document adding and management tools
Home-page: http://svn.plone.org/svn/collective/
Author: UNKNOWN
Author-email: UNKNOWN
License: GPL
Platform: UNKNOWN
Classifier: Framework :: Plone
Classifier: Programming Language :: Python
